README.md
setup.py
london_air_quality/__init__.py
london_air_quality.egg-info/PKG-INFO
london_air_quality.egg-info/SOURCES.txt
london_air_quality.egg-info/dependency_links.txt
london_air_quality.egg-info/requires.txt
london_air_quality.egg-info/top_level.txt