Metadata-Version: 1.2
Name: london-air-quality
Version: 0.1
Summary: Parse London air quality data
Home-page: https://github.com/robmarkcole/London-Air-Quality
Author: Robin Cole
Author-email: robmarkcole@gmail.com
License: Apache License, Version 2.0
Platform: UNKNOWN
Classifier: Intended Audience :: Developers
Classifier: Natural Language :: English
Classifier: Programming Language :: Python
Classifier: Programming Language :: Python :: 3
Requires-Python: >=3.6
